elf_checker/__init__.py
elf_checker/elf_checker.py
elf_checker/py.typed
elf_checker-1.0.1.dist-info/COPYING.md
elf_checker-1.0.1.dist-info/LICENSES/GTDGmbH.md
elf_checker-1.0.1.dist-info/METADATA
elf_checker-1.0.1.dist-info/WHEEL
elf_checker-1.0.1.dist-info/entry_points.txt
elf_checker-1.0.1.dist-info/RECORD
