Metadata-Version: 2.1
Name: elf-checker
Version: 1.0.1
Summary: A tool to visualize and check where ELF sections are located in different types of binaries
License: MPL-2.0
Author: Thomas Wucher
Author-email: thomas.wucher@gtd-gmbh.de
Requires-Python: >=3.9,<4.0
Classifier: License :: OSI Approved
Classifier: Programming Language :: Python :: 3
Classifier: Programming Language :: Python :: 3.9
Classifier: Programming Language :: Python :: 3.10
Classifier: Programming Language :: Python :: 3.11
Classifier: Programming Language :: Python :: 3.12
Requires-Dist: pyelftools (>=0.31,<0.32)
